ascend/__init__.py
ascend/agents.py
ascend/client.py
ascend/constants.py
ascend/exceptions.py
ascend/models.py
ascend/utils/__init__.py
ascend/utils/retry.py
ascend/utils/validation.py
ascend_ai_sdk-1.0.0.dist-info/licenses/LICENSE
ascend_ai_sdk-1.0.0.dist-info/METADATA
ascend_ai_sdk-1.0.0.dist-info/WHEEL
ascend_ai_sdk-1.0.0.dist-info/top_level.txt
ascend_ai_sdk-1.0.0.dist-info/RECORD
