Metadata-Version: 2.4
Name: ascend-ai-sdk
Version: 1.0.0
Summary: Official Python SDK for Ascend AI Governance Platform
Author-email: Ascend AI <sdk@ascendai.app>
License: MIT
Project-URL: Homepage, https://ascendai.app
Project-URL: Documentation, https://docs.ascendai.app/sdk/python
Project-URL: Repository, https://github.com/ascend-ai/ascend-sdk-python
Project-URL: Changelog, https://github.com/ascend-ai/ascend-sdk-python/blob/main/CHANGELOG.md
Keywords: ai,governance,authorization,security,compliance,agent
Classifier: Development Status :: 5 - Production/Stable
Classifier: Intended Audience :: Developers
Classifier: License :: OSI Approved :: MIT License
Classifier: Programming Language :: Python :: 3
Classifier: Programming Language :: Python :: 3.8
Classifier: Programming Language :: Python :: 3.9
Classifier: Programming Language :: Python :: 3.10
Classifier: Programming Language :: Python :: 3.11
Classifier: Programming Language :: Python :: 3.12
Classifier: Topic :: Software Development :: Libraries :: Python Modules
Classifier: Topic :: Security
Classifier: Topic :: Scientific/Engineering :: Artificial Intelligence
Requires-Python: >=3.8
License-File: LICENSE
Requires-Dist: requests>=2.28.0
Requires-Dist: python-dotenv>=1.0.0
Provides-Extra: dev
Requires-Dist: pytest>=7.0.0; extra == "dev"
Requires-Dist: pytest-cov>=4.0.0; extra == "dev"
Requires-Dist: black>=23.0.0; extra == "dev"
Requires-Dist: mypy>=1.0.0; extra == "dev"
Requires-Dist: types-requests>=2.28.0; extra == "dev"
Dynamic: license-file
Dynamic: requires-python
